neptune_scale/__init__.py
neptune_scale/api/__init__.py
neptune_scale/api/api_client.py
neptune_scale/core/__init__.py
neptune_scale/core/components/__init__.py
neptune_scale/core/components/abstract.py
neptune_scale/core/components/daemon.py
neptune_scale/core/components/errors_tracking.py
neptune_scale/core/components/operations_queue.py
neptune_scale/core/components/queue_element.py
neptune_scale/core/components/sync_process.py
neptune_scale/core/logger.py
neptune_scale/core/metadata_splitter.py
neptune_scale/core/process_killer.py
neptune_scale/core/serialization.py
neptune_scale/core/styles.py
neptune_scale/core/validation.py
neptune_scale/envs.py
neptune_scale/exceptions.py
neptune_scale/parameters.py
neptune_client_scale-0.2.0.dist-info/METADATA
neptune_client_scale-0.2.0.dist-info/WHEEL
neptune_client_scale-0.2.0.dist-info/RECORD
